K-means_SW-HW/rtl/comparator.v
module comparator_unit(
    // input squared obtained from the 3 distance units
    input wire[17:0] dist_0,
    input wire[17:0] dist_1,
    input wire[17:0] dist_2,

    // output is the cluster id
    output reg[1:0] cluster_id
);
    // this compared the distances squared obtained from the 3 units (can be scaled easily)
    // since this is a simple implementation with less to compare a combinational simple block works 
    // when working with more centroids research papers suggest to use a tournament tree to make it faster clock cycle wise(will do comparision over several clocks)
    // also in the higher centroid count recommended to use the traingular inequality and stuff to make it simpler

    // incase of tie default assigning lower numbered cluster
    always @(*) begin
        if(dist_0<=dist_1)begin
            if(dist_0<=dist_2) cluster_id = 2'b00;
            else cluster_id=2'b10;
        end else begin
            if(dist_1<=dist_2) cluster_id = 2'b01;
            else cluster_id=2'b10;
        end
    end
    
endmodule

K-means_SW-HW/rtl/functional_blocks/distance_unit.v
module distance_core (
    // rgb values of the inputed pixel
    input  wire[7:0] pixel_r,
    input  wire[7:0] pixel_g,
    input  wire[7:0] pixel_b,

    // 8-bit rgb values of the target centroid
    input  wire[7:0] centroid_r,
    input  wire[7:0] centroid_g,
    input  wire[7:0] centroid_b,

    // the 18-bit squared distance result
    // (18 bits is required because 3 * (255^2) = 195,075, which takes 18 bits)
    output wire[17:0] sq_distance
);
    // this is the backbone of the project this will be used to find the distances
    // more than one such module will be instantiated to make use of parallel computation
    // all of the work will be done on the square of the distances instead of sq root as sq root module is expensive of hardware

    // NO NEED TO USE SIGNED DATA TYPE AS DISTANCES ARE SQUARED

    // this is just calculation in 3d D2 = (PR-CR)2 + (PG-CG)2 + (PB-CB)2
    // temp wires
    wire[17:0] Sr;
    wire[17:0] Sb;
    wire[17:0] Sg;

    assign Sr= ((pixel_r-centroid_r)*(pixel_r-centroid_r)) ;
    assign Sb= ((pixel_b-centroid_b)*(pixel_b-centroid_b)) ;
    assign Sg= ((pixel_g-centroid_g)*(pixel_g-centroid_g)) ;

    assign sq_distance= Sr+Sb+Sg;

endmodule

K-means_inference/rtl/functional_blocks/uart_tx.v
`timescale 1ns / 1ps

module uart_tx #(
    parameter CLKS_PER_BIT = 234 // 27MHz / 115200 Baud
)(
    input  wire clk,
    input  wire tx_start,  // Trigger pulse to send
    input  wire[7:0] tx_byte,   // Data to send
    output reg tx_busy = 0, // 1 = Busy, 0 = Ready
    output reg tx_pin  = 1  
);
    reg [1:0] txState = 0; //state reg
    reg [12:0] txCounter = 0;   // to count no of clock cycle
    reg [2:0] txBitNumber = 0; // no of bits sent
    reg [7:0] dataToTx = 0;    // data copied temporarily 

    // FSM States
    localparam [1:0]
        IDLE = 2'd0,
        START_BIT = 2'd1,
        DATA = 2'd2,
        STOP_BIT = 2'd3;

    always @(posedge clk) begin
        case(txState)
            
            IDLE: begin
                tx_pin  <= 1'b1; // Idle HIGH
                tx_busy <= 1'b0; // Ready for data
                txCounter   <= 0;
                txBitNumber <= 0;

                if (tx_start == 1'b1) begin
                    tx_busy  <= 1'b1;      // Lock interface
                    dataToTx <= tx_byte; 
                    txState  <= START_BIT; 
                end
            end
            
            START_BIT: begin
                tx_pin <= 1'b0; // Start bit is LOW
                
                if ((txCounter + 1) == CLKS_PER_BIT) begin
                    txCounter <= 0;
                    txState   <= DATA; 
                end else begin
                    txCounter <= txCounter + 1;
                end
            end
            
            DATA: begin
                tx_pin <= dataToTx[txBitNumber]; // Drive current bit
                
                if ((txCounter + 1) == CLKS_PER_BIT) begin
                    txCounter <= 0; 
                    
                    if (txBitNumber == 3'b111) begin
                        txState <= STOP_BIT; // 8 bits sent
                    end else begin
                        txBitNumber <= txBitNumber + 1; 
                    end
                end else begin
                    txCounter <= txCounter + 1;
                end
            end
            
            STOP_BIT: begin
                tx_pin <= 1'b1; // Stop bit is HIGH
                
                if ((txCounter + 1) == CLKS_PER_BIT) begin
                    txCounter <= 0;
                    txState   <= IDLE; // Frame done
                end else begin
                    txCounter <= txCounter + 1;
                end
            end
            
            default: txState <= IDLE;
            
        endcase
    end

endmodule

K-means_SW-HW/rtl/functional_blocks/uart_rx.v
`timescale 1ns / 1ps

module uart_rx #(
    // 27,000,000 Hz / 115,200 Baud = ~234
    // its parametrized so can be changed according to the need
    parameter CLKS_PER_BIT = 234 
)(
    input  wire clk,       // 27 MHz System Clock
    input  wire rx_pin,    //(1 = Idle, 0 = Start)
    output reg[7:0] rx_byte,   // 8bit data
    output reg rx_ready   // Goes HIGH for exactly 1 clock cycle when data is valid
);

    localparam  HALF_CLK_CYCLE = CLKS_PER_BIT/2;

    reg [3:0] rxState = 0;// state if the uart in fsm
    reg [12:0] rxCounter = 0;//clk cycle counter
    reg [2:0] rxBitNumber = 0;//no of bits or bit count
    reg [7:0] dataIn = 0;//temp reg to store the data before valid is hit (prolly a sipo mode reg)
    reg byteReady = 0;//flagged 0 when output is ready
    
    // fsm states
    localparam[2:0]
    IDLE = 0,
    START_BIT = 1,
    READ_WAIT = 2,
    READ = 3,
    STOP =4;

    // the core fsm logic
    always @(posedge clk) begin
        case(rxState) 
            IDLE: begin
                rx_ready <= 0;    // Reset the flag!
                rxCounter <= 1;   // Reset the stopwatch!
                rxBitNumber <= 0;
                if(rx_pin == 1'b0) begin
                    rxState <= START_BIT;
                end
            end
            START_BIT: begin
                if(rxCounter == HALF_CLK_CYCLE)begin
                    rxState <= READ_WAIT;
                    rxCounter<=1;
                end
                else begin
                    rxCounter <= rxCounter + 1;
                end
            end
            READ_WAIT: begin
                rxCounter <= rxCounter + 1;
                if((rxCounter+1) == CLKS_PER_BIT)begin
                    rxState <= READ;
                end
            end
            READ: begin
                // push the data in shift reg
                rxCounter<=1;
                rxBitNumber <= rxBitNumber+1;
                rx_byte <= {rx_pin, rx_byte[7:1]};
                if (rxBitNumber == 3'b111) begin
                    rxState <= STOP;
                end else begin
                    rxState <= READ_WAIT;
                end
            end
            STOP: begin
                rxCounter <= rxCounter + 1;
                if ((rxCounter + 1) == CLKS_PER_BIT) begin
                    rxState <= IDLE;
                    rxCounter <= 0;
                    rx_ready <=1;
                end
            end
        endcase
    end

endmodule

K-means_SW-HW/rtl/inference.v
`timescale 1ns / 1ps

// note debugging
// case of false positive occured where tx_state was not initialised it worked for the simulation but didnt work on fpga
// always look out and check in the waveform to see if any core signal doesnt go uninitialised or gives X

module inference (
    input  wire clk,      // 27 MHz clock 
    input  wire rx_pin,   // UART RX PIN
    output wire tx_pin,   // UART TX PIN
    output wire [5:0] led // debugging
);

    // so right now this is a inference model that only classify with given centroid then will be building the same for dynamic centroids
    localparam [7:0] C1_R = 8'hFF, C1_G = 8'h00, C1_B = 8'h00; // Centroid 1: Red
    localparam [7:0] C2_R = 8'h00, C2_G = 8'hFF, C2_B = 8'h00; // Centroid 2: Green
    localparam [7:0] C3_R = 8'h00, C3_G = 8'h00, C3_B = 8'hFF; // Centroid 3: Blue
    // basically we will classify the incoming pixels into R or G or B

    // uart wires
    wire[7:0] rx_byte;
    wire rx_ready;
    reg tx_start = 0;
    reg[7:0] tx_byte  = 0;
    wire tx_busy;

    //recieved pixels
    reg [7:0] R = 0;
    reg [7:0] G = 0;
    reg [7:0] B = 0;

    wire[1:0] winning_cluster;

    // core logic starts here
    wire[17:0] dis1;
    wire[17:0] dis2;
    wire[17:0] dis3;

    uart_rx rx (.clk(clk), .rx_pin(rx_pin), .rx_byte(rx_byte), .rx_ready(rx_ready));
    uart_tx tx (.clk(clk), .tx_start(tx_start), .tx_byte(tx_byte), .tx_busy(tx_busy), .tx_pin(tx_pin));

    distance_core d1(.sq_distance(dis1), .pixel_r(R) , .pixel_b(B) , .pixel_g(G) , .centroid_r(C1_R), .centroid_b(C1_B) , .centroid_g(C1_G));
    distance_core d2(.sq_distance(dis2), .pixel_r(R) , .pixel_b(B) , .pixel_g(G) , .centroid_r(C2_R), .centroid_b(C2_B) , .centroid_g(C2_G));
    distance_core d3(.sq_distance(dis3), .pixel_r(R) , .pixel_b(B) , .pixel_g(G) , .centroid_r(C3_R), .centroid_b(C3_B) , .centroid_g(C3_G));

    comparator_unit comp(.cluster_id(winning_cluster) , .dist_0(dis1) , .dist_1(dis2) , .dist_2(dis3));

    // fsm states
    localparam[2:0]
    Wait_R = 0,
    Wait_G = 1,
    Wait_B = 2,
    Compute = 3,
    Transmit = 4;

    reg[2:0] tx_state;

    always @(posedge clk) begin
        tx_start<=0;
        case (tx_state)
            Wait_R : begin
                if(rx_ready) begin
                    R<=rx_byte;
                    tx_state<=Wait_G;
                end
            end
            Wait_G : begin
                if(rx_ready) begin
                    G<=rx_byte;
                    tx_state<=Wait_B;
                end
            end
            Wait_B : begin
                if(rx_ready) begin
                    B<=rx_byte;
                    tx_state<=Compute;
                end
            end
            Compute : begin
                tx_byte<={6'd0,winning_cluster};
                tx_state<=Transmit;
            end
            Transmit : begin
                if (!tx_busy) begin
                    tx_start <= 1'b1;  
                    tx_state<= Wait_R; 
                end
            end
            default : tx_state = 2'b00;
        endcase
    end

    assign led = ~{4'b0000, winning_cluster};

endmodule

K-means_SW-HW/tb/tb_inference.v
`timescale 1ns / 1ps

module tb_inference;

    reg clk;
    reg rx_pin;
    wire tx_pin;
    wire [5:0] led;

    // 1. Instantiate Your Module
    inference uut (
        .clk(clk),
        .rx_pin(rx_pin),
        .tx_pin(tx_pin),
        .led(led)
    );

    // 2. Generate the 27 MHz Clock (~37ns period)
    initial clk = 0;
    always #18.5 clk = ~clk;

    // Timing calculation: 234 ticks * 37ns = 8658ns per bit
    localparam BIT_PERIOD = 234 * 37;

    // --- SELF CHECKING VARIABLES ---
    reg [1:0] expected_cluster;
    integer error_count = 0;
    // -------------------------------

    // 3. PC Transmitter Task (Sends 1 Byte to FPGA)
    task send_byte(input [7:0] data);
        integer i;
        begin
            rx_pin = 1'b0; // Start Bit
            #(BIT_PERIOD);
            for (i = 0; i < 8; i = i + 1) begin
                rx_pin = data[i]; // Data Bits
                #(BIT_PERIOD);
            end
            rx_pin = 1'b1; // Stop Bit
            #(BIT_PERIOD);
        end
    endtask

    // 4. PC Pixel Streamer (Sends R, G, B sequentially)
    task send_pixel(input [7:0] r, input [7:0] g, input [7:0] b);
        begin
            send_byte(r);
            #(BIT_PERIOD); 
            send_byte(g);
            #(BIT_PERIOD);
            send_byte(b);
        end
    endtask

    // 5. PC Receiver & Checker Logic
    reg [7:0] captured_byte;
    integer j;
    initial begin
        forever begin
            // Wait for the TX wire to drop (Start Bit from FPGA)
            @(negedge tx_pin);
            
            #(BIT_PERIOD / 2); // Center read head
            #(BIT_PERIOD);     // Move to first bit
            
            // Read all 8 bits
            for (j = 0; j < 8; j = j + 1) begin
                captured_byte[j] = tx_pin;
                #(BIT_PERIOD);
            end
            #(BIT_PERIOD); // Wait out Stop Bit
            
            // SELF-CHECKING LOGIC
            if (captured_byte[1:0] === expected_cluster) begin
                $display("[PASS] FPGA returned %d. Matches expected!", captured_byte[1:0]);
            end else begin
                $display("[FAIL] FPGA returned %d. Expected %d!", captured_byte[1:0], expected_cluster);
                error_count = error_count + 1;
            end
        end
    end

    // 6. The Master Test Sequence
    initial begin
        $dumpfile("sim.vcd");
        $dumpvars(0, tb_inference);

        // Initialize line
        rx_pin = 1'b1;
        #1000;

        // Test Case 1: purely RED pixel -> Expect Cluster 0
        expected_cluster = 2'd0;
        $display("[SIM TIME: %0t ns] Sending RED Pixel...", $time);
        send_pixel(8'hFF, 8'h00, 8'h00);
        #500000;

        // Test Case 2: purely GREEN pixel -> Expect Cluster 1
        expected_cluster = 2'd1;
        $display("[SIM TIME: %0t ns] Sending GREEN Pixel...", $time);
        send_pixel(8'h00, 8'hFF, 8'h00);
        #500000;

        // Test Case 3: purely BLUE pixel -> Expect Cluster 2
        expected_cluster = 2'd2;
        $display("[SIM TIME: %0t ns] Sending BLUE Pixel...", $time);
        send_pixel(8'h00, 8'h00, 8'hFF);
        #500000;

        // Test Case 4: MIXED pixel (Mostly Green) -> Expect Cluster 1
        expected_cluster = 2'd1;
        $display("[SIM TIME: %0t ns] Sending DARK GREEN Pixel...", $time);
        send_pixel(8'd10, 8'd200, 8'd50);
        #500000;

        // Print final summary
        $display("========================================");
        if (error_count == 0) begin
            $display("  ALL TESTS PASSED! (0 Errors)");
        end else begin
            $display("  SIMULATION FAILED WITH %d ERRORS.", error_count);
        end
        $display("========================================");
        
        $finish;
    end

endmodule

K-means_SW-HW/sim.vcd
$date
	Thu Jun 25 13:52:05 2026
$end
$version
	Icarus Verilog
$end
$timescale
	1ps
$end
$scope module tb_inference $end
$var wire 1 ! tx_pin $end
$var wire 6 " led [5:0] $end
$var parameter 64 # BIT_PERIOD $end
$var reg 8 $ captured_byte [7:0] $end
$var reg 1 % clk $end
$var reg 2 & expected_cluster [1:0] $end
$var reg 1 ' rx_pin $end
$var integer 32 ( error_count [31:0] $end
$var integer 32 ) j [31:0] $end
$scope module uut $end
$var wire 1 % clk $end
$var wire 6 * led [5:0] $end
$var wire 1 ' rx_pin $end
$var wire 2 + winning_cluster [1:0] $end
$var wire 1 ! tx_pin $end
$var wire 1 , tx_busy $end
$var wire 1 - rx_ready $end
$var wire 8 . rx_byte [7:0] $end
$var wire 18 / dis3 [17:0] $end
$var wire 18 0 dis2 [17:0] $end
$var wire 18 1 dis1 [17:0] $end
$var parameter 8 2 C1_B $end
$var parameter 8 3 C1_G $end
$var parameter 8 4 C1_R $end
$var parameter 8 5 C2_B $end
$var parameter 8 6 C2_G $end
$var parameter 8 7 C2_R $end
$var parameter 8 8 C3_B $end
$var parameter 8 9 C3_G $end
$var parameter 8 : C3_R $end
$var parameter 3 ; Compute $end
$var parameter 3 < Transmit $end
$var parameter 3 = Wait_B $end
$var parameter 3 > Wait_G $end
$var parameter 3 ? Wait_R $end
$var reg 8 @ B [7:0] $end
$var reg 8 A G [7:0] $end
$var reg 8 B R [7:0] $end
$var reg 8 C tx_byte [7:0] $end
$var reg 1 D tx_start $end
$var reg 3 E tx_state [2:0] $end
$scope module comp $end
$var wire 18 F dist_2 [17:0] $end
$var wire 18 G dist_1 [17:0] $end
$var wire 18 H dist_0 [17:0] $end
$var reg 2 I cluster_id [1:0] $end
$upscope $end
$scope module d1 $end
$var wire 8 J centroid_b [7:0] $end
$var wire 8 K centroid_g [7:0] $end
$var wire 8 L centroid_r [7:0] $end
$var wire 8 M pixel_b [7:0] $end
$var wire 8 N pixel_g [7:0] $end
$var wire 8 O pixel_r [7:0] $end
$var wire 18 P sq_distance [17:0] $end
$var wire 18 Q Sr [17:0] $end
$var wire 18 R Sg [17:0] $end
$var wire 18 S Sb [17:0] $end
$upscope $end
$scope module d2 $end
$var wire 8 T centroid_b [7:0] $end
$var wire 8 U centroid_g [7:0] $end
$var wire 8 V centroid_r [7:0] $end
$var wire 8 W pixel_b [7:0] $end
$var wire 8 X pixel_g [7:0] $end
$var wire 8 Y pixel_r [7:0] $end
$var wire 18 Z sq_distance [17:0] $end
$var wire 18 [ Sr [17:0] $end
$var wire 18 \ Sg [17:0] $end
$var wire 18 ] Sb [17:0] $end
$upscope $end
$scope module d3 $end
$var wire 8 ^ centroid_b [7:0] $end
$var wire 8 _ centroid_g [7:0] $end
$var wire 8 ` centroid_r [7:0] $end
$var wire 8 a pixel_b [7:0] $end
$var wire 8 b pixel_g [7:0] $end
$var wire 8 c pixel_r [7:0] $end
$var wire 18 d sq_distance [17:0] $end
$var wire 18 e Sr [17:0] $end
$var wire 18 f Sg [17:0] $end
$var wire 18 g Sb [17:0] $end
$upscope $end
$scope module rx $end
$var wire 1 % clk $end
$var wire 1 ' rx_pin $end
$var parameter 32 h CLKS_PER_BIT $end
$var parameter 32 i HALF_CLK_CYCLE $end
$var parameter 3 j IDLE $end
$var parameter 3 k READ $end
$var parameter 3 l READ_WAIT $end
$var parameter 3 m START_BIT $end
$var parameter 3 n STOP $end
$var reg 1 o byteReady $end
$var reg 8 p dataIn [7:0] $end
$var reg 3 q rxBitNumber [2:0] $end
$var reg 13 r rxCounter [12:0] $end
$var reg 4 s rxState [3:0] $end
$var reg 8 t rx_byte [7:0] $end
$var reg 1 - rx_ready $end
$upscope $end
$scope module tx $end
$var wire 1 % clk $end
$var wire 8 u tx_byte [7:0] $end
$var wire 1 D tx_start $end
$var parameter 32 v CLKS_PER_BIT $end
$var parameter 2 w DATA $end
$var parameter 2 x IDLE $end
$var parameter 2 y START_BIT $end
$var parameter 2 z STOP_BIT $end
$var reg 8 { dataToTx [7:0] $end
$var reg 3 | txBitNumber [2:0] $end
$var reg 13 } txCounter [12:0] $end
$var reg 2 ~ txState [1:0] $end
$var reg 1 , tx_busy $end
$var reg 1 ! tx_pin $end
$upscope $end
$upscope $end
$scope task send_byte $end
$var reg 8 !" data [7:0] $end
$var integer 32 "" i [31:0] $end
$upscope $end
$scope task send_pixel $end
$var reg 8 #" b [7:0] $end
$var reg 8 $" g [7:0] $end
$var reg 8 %" r [7:0] $end
$upscope $end
$upscope $end
$enddefinitions $end
$comment Show the parameter values. $end
$dumpall
b11 z
b1 y
b0 x
b10 w
b11101010 v
b100 n
b1 m
b10 l
b11 k
b0 j
b1110101 i
b11101010 h
b0 ?
b1 >
b10 =
b100 <
b11 ;
b0 :
b0 9
b11111111 8
b0 7
b11111111 6
b0 5
b11111111 4
b0 3
b0 2
b10000111010010 #
$end
#0
$dumpvars
bx %"
bx $"
bx #"
bx ""
bx !"
b0 ~
b0 }
b0 |
b0 {
b0 u
bx t
b0 s
b0 r
b0 q
b0 p
0o
b1111111000000001 g
b0 f
b0 e
b1111111000000001 d
b0 c
b0 b
b0 a
b0 `
b0 _
b11111111 ^
b0 ]
b1111111000000001 \
b0 [
b1111111000000001 Z
b0 Y
b0 X
b0 W
b0 V
b11111111 U
b0 T
b0 S
b0 R
b1111111000000001 Q
b1111111000000001 P
b0 O
b0 N
b0 M
b11111111 L
b0 K
b0 J
b0 I
b1111111000000001 H
b1111111000000001 G
b1111111000000001 F
b0 E
0D
b0 C
b0 B
b0 A
b0 @
b1111111000000001 1
b1111111000000001 0
b1111111000000001 /
bx .
x-
0,
b0 +
b111111 *
bx )
b0 (
1'
bx &
0%
bx $
b111111 "
1!
$end
#18500
b1 r
0-
1%
#37000
0%
#55500
1%
#74000
0%
#92500
1%
#111000
0%
#129500
1%
#148000
0%
#166500
1%
#185000
0%
#203500
1%
#222000
0%
#240500
1%
#259000
0%
#277500
1%
#296000
0%
#314500
1%
#333000
0%
#351500
1%
#370000
0%
#388500
1%
#407000
0%
#425500
1%
#444000
0%
#462500
1%
#481000
0%
#499500
1%
#518000
0%
#536500
1%
#555000
0%
#573500
1%
#592000
0%
#610500
1%
#629000
0%
#647500
1%
#666000
0%
#684500
1%
#703000
0%
#721500
1%
#740000
0%
#758500
1%
#777000
0%
#795500
1%
#814000
0%
#832500
1%
#851000
0%
#869500
1%
#888000
0%
#906500
1%
#925000
0%
#943500
1%
#962000
0%
#980500
1%
#999000
0%
#1000000
0'
b11111111 !"
b0 #"
b0 $"
b11111111 %"
b0 &
#1017500
b1 s
1%
#1036000
0%
#1054500
b10 r
1%
#1073000
0%
#1091500
b11 r
1%
#1110000
0%
#1128500
b100 r
1%
#1147000
0%
#1165500
b101 r
1%
#1184000
0%
#1202500
b110 r
1%
#1221000
0%
#1239500
b111 r
1%
#1258000
0%
#1276500
b1000 r
1%
#1295000
0%
#1313500
b1001 r
1%
#1332000
0%
#1350500
b1010 r
1%
#1369000
0%
#1387500
b1011 r
1%
#1406000
0%
#1424500
b1100 r
1%
#1443000
0%
#1461500
b1101 r
1%
#1480000
0%
#1498500
b1110 r
1%
#1517000
0%
#1535500
b1111 r
1%
#1554000
0%
#1572500
b10000 r
1%
#1591000
0%
#1609500
b10001 r
1%
#1628000
0%
#1646500
b10010 r
1%
#1665000
0%
#1683500
b10011 r
1%
#1702000
0%
#1720500
b10100 r
1%
#1739000
0%
#1757500
b10101 r
1%
#1776000
0%
#1794500
b10110 r
1%
#1813000
0%
#1831500
b10111 r
1%
#1850000
0%
#1868500
b11000 r
1%
#1887000
0%
#1905500
b11001 r
1%
#1924000
0%
#1942500
b11010 r
1%
#1961000
0%
#1979500
b11011 r
1%
#1998000
0%
#2016500
b11100 r
1%
#2035000
0%
#2053500
b11101 r
1%
#2072000
0%
#2090500
b11110 r
1%
#2109000
0%
#2127500
b11111 r
1%
#2146000
0%
#2164500
b100000 r
1%
#2183000
0%
#2201500
b100001 r
1%
#2220000
0%
#2238500
b100010 r
1%
#2257000
0%
#2275500
b100011 r
1%
#2294000
0%
#2312500
b100100 r
1%
#2331000
0%
#2349500
b100101 r
1%
#2368000
0%
#2386500
b100110 r
1%
#2405000
0%
#2423500
b100111 r
1%
#2442000
0%
#2460500
b101000 r
1%
#2479000
0%
#2497500
b101001 r
1%
#2516000
0%
#2534500
b101010 r
1%
#2553000
0%
#2571500
b101011 r
1%
#2590000
0%
#2608500
b101100 r
1%
#2627000
0%
#2645500
b101101 r
1%
#2664000
0%
#2682500
b101110 r
1%
#2701000
0%
#2719500
b101111 r
1%
#2738000
0%
#2756500
b110000 r
1%
#2775000
0%
#2793500
b110001 r
1%
#2812000
0%
#2830500
b110010 r
1%
#2849000
0%
#2867500
b110011 r
1%
#2886000
0%
#2904500
b110100 r
1%
#2923000
0%
#2941500
b110101 r
1%
#2960000
0%
#2978500
b110110 r
1%
#2997000
0%
#3015500
b110111 r
1%
#3034000
0%
#3052500
b111000 r
1%
#3071000
0%
#3089500
b111001 r
1%
#3108000
0%
#3126500
b111010 r
1%
#3145000
0%
#3163500
b111011 r
1%
#3182000
0%
#3200500
b111100 r
1%
#3219000
0%
#3237500
b111101 r
1%
#3256000
0%
#3274500
b111110 r
1%
#3293000
0%
#3311500
b111111 r
1%
#3330000
0%
#3348500
b1000000 r
1%
#3367000
0%
#3385500
b1000001 r
1%
#3404000
0%
#3422500
b1000010 r
1%
#3441000
0%
#3459500
b1000011 r
1%
#3478000
0%
#3496500
b1000100 r
1%
#3515000
0%
#3533500
b1000101 r
1%
#3552000
0%
#3570500
b1000110 r
1%
#3589000
0%
#3607500
b1000111 r
1%
#3626000
0%
#3644500
b1001000 r
1%
#3663000
0%
#3681500
b1001001 r
1%
#3700000
0%
#3718500
b1001010 r
1%
#3737000
0%
#3755500
b1001011 r
1%
#3774000
0%
#3792500
b1001100 r
1%
#3811000
0%
#3829500
b1001101 r
1%
#3848000
0%
#3866500
b1001110 r
1%
#3885000
0%
#3903500
b1001111 r
1%
#3922000
0%
#3940500
b1010000 r
1%
#3959000
0%
#3977500
b1010001 r
1%
#3996000
0%
#4014500
b1010010 r
1%
#4033000
0%
#4051500
b1010011 r
1%
#4070000
0%
#4088500
b1010100 r
1%
#4107000
0%
#4125500
b1010101 r
1%
#4144000
0%
#4162500
b1010110 r
1%
#4181000
0%
#4199500
b1010111 r
1%
#4218000
0%
#4236500
b1011000 r
1%
#4255000
0%
#4273500
b1011001 r
1%
#4292000
0%
#4310500
b1011010 r
1%
#4329000
0%
#4347500
b1011011 r
1%
#4366000
0%
#4384500
b1011100 r
1%
#4403000
0%
#4421500
b1011101 r
1%
#4440000
0%
#4458500
b1011110 r
1%
#4477000
0%
#4495500
b1011111 r
1%
#4514000
0%
#4532500
b1100000 r
1%
#4551000
0%
#4569500
b1100001 r
1%
#4588000
0%
#4606500
b1100010 r
1%
#4625000
0%
#4643500
b1100011 r
1%
#4662000
0%
#4680500
b1100100 r
1%
#4699000
0%
#4717500
b1100101 r
1%
#4736000
0%
#4754500
b1100110 r
1%
#4773000
0%
#4791500
b1100111 r
1%
#4810000
0%
#4828500
b1101000 r
1%
#4847000
0%
#4865500
b1101001 r
1%
#4884000
0%
#4902500
b1101010 r
1%
#4921000
0%
#4939500
b1101011 r
1%
#4958000
0%
#4976500
b1101100 r
1%
#4995000
0%
#5013500
b1101101 r
1%
#5032000
0%
#5050500
b1101110 r
1%
#5069000
0%
#5087500
b1101111 r
1%
#5106000
0%
#5124500
b1110000 r
1%
#5143000
0%
#5161500
b1110001 r
1%
#5180000
0%
#5198500
b1110010 r
1%
#5217000
0%
#5235500
b1110011 r
1%
#5254000
0%
#5272500
b1110100 r
1%
#5291000
0%
#5309500
b1110101 r
1%
#5328000
0%
#5346500
b1 r
b10 s
1%
#5365000
0%
#5383500
b10 r
1%
#5402000
0%
#5420500
b11 r
1%
#5439000
0%
#5457500
b100 r
1%
#5476000
0%
#5494500
b101 r
1%
#5513000
0%
#5531500
b110 r
1%
#5550000
0%
#5568500
b111 r
1%
#5587000
0%
#5605500
b1000 r
1%
#5624000
0%
#5642500
b1001 r
1%
#5661000
0%
#5679500
b1010 r
1%
#5698000
0%
#5716500
b1011 r
1%
#5735000
0%
#5753500
b1100 r
1%
#5772000
0%
#5790500
b1101 r
1%
#5809000
0%
#5827500
b1110 r
1%
#5846000
0%
#5864500
b1111 r
1%
#5883000
0%
#5901500
b10000 r
1%
#5920000
0%
#5938500
b10001 r
1%
#5957000
0%
#5975500
b10010 r
1%
#5994000
0%
#6012500
b10011 r
1%
#6031000
0%
#6049500
b10100 r
1%
#6068000
0%
#6086500
b10101 r
1%
#6105000
0%
#6123500
b10110 r
1%
#6142000
0%
#6160500
b10111 r
1%
#6179000
0%
#6197500
b11000 r
1%
#6216000
0%
#6234500
b11001 r
1%
#6253000
0%
#6271500
b11010 r
1%
#6290000
0%
#6308500
b11011 r
1%
#6327000
0%
#6345500
b11100 r
1%
#6364000
0%
#6382500
b11101 r
1%
#6401000
0%
#6419500
b11110 r
1%
#6438000
0%
#6456500
b11111 r
1%
#6475000
0%
#6493500
b100000 r
1%
#6512000
0%
#6530500
b100001 r
1%
#6549000
0%
#6567500
b100010 r
1%
#6586000
0%
#6604500
b100011 r
1%
#6623000
0%
#6641500
b100100 r
1%
#6660000
0%
#6678500
b100101 r
1%
#6697000
0%
#6715500
b100110 r
1%
#6734000
0%
#6752500
b100111 r
1%
#6771000
0%
#6789500
b101000 r
1%
#6808000
0%
#6826500
b101001 r
1%
#6845000
0%
#6863500
b101010 r
1%
#6882000
0%
#6900500
b101011 r
1%
#6919000
0%
#6937500
b101100 r
1%
#6956000
0%
#6974500
b101101 r
1%
#6993000
0%
#7011500
b101110 r
1%
#7030000
0%
#7048500
b101111 r
1%
#7067000
0%
#7085500
b110000 r
1%
#7104000
0%
#7122500
b110001 r
1%
#7141000
0%
#7159500
b110010 r
1%
#7178000
0%
#7196500
b110011 r
1%
#7215000
0%
#7233500
b110100 r
1%
#7252000
0%
#7270500
b110101 r
1%
#7289000
0%
#7307500
b110110 r
1%
#7326000
0%
#7344500
b110111 r
1%
#7363000
0%
#7381500
b111000 r
1%
#7400000
0%
#7418500
b111001 r
1%
#7437000
0%
#7455500
b111010 r
1%
#7474000
0%
#7492500
b111011 r
1%
#7511000
0%
#7529500
b111100 r
1%
#7548000
0%
#7566500
b111101 r
1%
#7585000
0%
#7603500
b111110 r
1%
#7622000
0%
#7640500
b111111 r
1%
#7659000
0%
#7677500
b1000000 r
1%
#7696000
0%
#7714500
b1000001 r
1%
#7733000
0%
#7751500
b1000010 r
1%
#7770000
0%
#7788500
b1000011 r
1%
#7807000
0%
#7825500
b1000100 r
1%
#7844000
0%
#7862500
b1000101 r
1%
#7881000
0%
#7899500
b1000110 r
1%
#7918000
0%
#7936500
b1000111 r
1%
#7955000
0%
#7973500
b1001000 r
1%
#7992000
0%
#8010500
b1001001 r
1%
#8029000
0%
#8047500
b1001010 r
1%
#8066000
0%
#8084500
b1001011 r
1%
#8103000
0%
#8121500
b1001100 r
1%
#8140000
0%
#8158500
b1001101 r
1%
#8177000
0%
#8195500
b1001110 r
1%
#8214000
0%
#8232500
b1001111 r
1%
#8251000
0%
#8269500
b1010000 r
1%
#8288000
0%
#8306500
b1010001 r
1%
#8325000
0%
#8343500
b1010010 r
1%
#8362000
0%
#8380500
b1010011 r
1%
#8399000
0%
#8417500
b1010100 r
1%
#8436000
0%
#8454500
b1010101 r
1%
#8473000
0%
#8491500
b1010110 r
1%
#8510000
0%
#8528500
b1010111 r
1%
#8547000
0%
#8565500
b1011000 r
1%
#8584000
0%
#8602500
b1011001 r
1%
#8621000
0%
#8639500
b1011010 r
1%
#8658000
0%
#8676500
b1011011 r
1%
#8695000
0%
#8713500
b1011100 r
1%
#8732000
0%
#8750500
b1011101 r
1%
#8769000
0%
#8787500
b1011110 r
1%
#8806000
0%
#8824500
b1011111 r
1%
#8843000
0%
#8861500
b1100000 r
1%
#8880000
0%
#8898500
b1100001 r
1%
#8917000
0%
#8935500
b1100010 r
1%
#8954000
0%
#8972500
b1100011 r
1%
#8991000
0%
#9009500
b1100100 r
1%
#9028000
0%
#9046500
b1100101 r
1%
#9065000
0%
#9083500
b1100110 r
1%
#9102000
0%
#9120500
b1100111 r
1%
#9139000
0%
#9157500
b1101000 r
1%
#9176000
0%
#9194500
b1101001 r
1%
#9213000
0%
#9231500
b1101010 r
1%
#9250000
0%
#9268500
b1101011 r
1%
#9287000
0%
#9305500
b1101100 r
1%
#9324000
0%
#9342500
b1101101 r
1%
#9361000
0%
#9379500
b1101110 r
1%
#9398000
0%
#9416500
b1101111 r
1%
#9435000
0%
#9453500
b1110000 r
1%
#9472000
0%
#9490500
b1110001 r
1%
#9509000
0%
#9527500
b1110010 r
1%
#9546000
0%
#9564500
b1110011 r
1%
#9583000
0%
#9601500
b1110100 r
1%
#9620000
0%
#9638500
b1110101 r
1%
#9657000
0%
#9658000
1'
b0 ""
#9675500
b1110110 r
1%
#9694000
0%
#9712500
b1110111 r
1%
#9731000
0%
#9749500
b1111000 r
1%
#9768000
0%
#9786500
b1111001 r
1%
#9805000
0%
#9823500
b1111010 r
1%
#9842000
0%
#9860500
b1111011 r
1%
#9879000
0%
#9897500
b1111100 r
1%
#9916000
0%
#9934500
b1111101 r
1%
#9953000
0%
#9971500
b1111110 r
1%
